desktop_notify/__init__.py
desktop_notify/action.py
desktop_notify/consts.py
desktop_notify/notify.py
desktop_notify/server.py
desktop_notify/aio/__init__.py
desktop_notify/aio/message_bus.py
desktop_notify/aio/notify.py
desktop_notify/aio/server.py
desktop_notify/glib/__init__.py
desktop_notify/glib/message_bus.py
desktop_notify/glib/notify.py
desktop_notify/glib/server.py
desktop_notify-1.3.3.dist-info/LICENSE
desktop_notify-1.3.3.dist-info/METADATA
desktop_notify-1.3.3.dist-info/WHEEL
desktop_notify-1.3.3.dist-info/entry_points.txt
desktop_notify-1.3.3.dist-info/top_level.txt
desktop_notify-1.3.3.dist-info/RECORD
