Metadata-Version: 2.1
Name: desktop-notify
Version: 1.3.3
Summary: Util for sending desktop notifications over dbus.
Home-page: https://gitlab.com/hxss-linux/desktop-notify
Author: hxss
Author-email: hxss@ya.ru
License: UNKNOWN
Platform: UNKNOWN
Classifier: Programming Language :: Python :: 3.8
Classifier: License :: OSI Approved :: MIT License
Classifier: Operating System :: POSIX :: Linux
Classifier: Topic :: Utilities
Requires-Python: >=3.8
